requests_gracedb/__init__.py
requests_gracedb/_version.py
requests_gracedb/auth.py
requests_gracedb/cert_reload.py
requests_gracedb/errors.py
requests_gracedb/file.py
requests_gracedb/scitoken.py
requests_gracedb/user_agent.py
requests_gracedb-0.2.2.dist-info/licenses/LICENSE.md
requests_gracedb-0.2.2.dist-info/METADATA
requests_gracedb-0.2.2.dist-info/WHEEL
requests_gracedb-0.2.2.dist-info/top_level.txt
requests_gracedb-0.2.2.dist-info/RECORD
