Metadata-Version: 2.4
Name: requests-gracedb
Version: 0.2.2
Summary: generic connection pooling HTTP client for GraceDB and similar services
Author-email: Leo Singer <leo.p.singer@nasa.gov>
License-Expression: GPL-3.0-or-later
Project-URL: source, https://git.ligo.org/emfollow/requests-gracedb
Project-URL: Bug Tracker, https://git.ligo.org/emfollow/requests-gracedb/issues
Project-URL: Documentation, https://requests-gracedb.readthedocs.io/
Project-URL: Source Code, https://git.ligo.org/emfollow/requests-gracedb
Classifier: Development Status :: 4 - Beta
Classifier: Environment :: Console
Classifier: Intended Audience :: Science/Research
Classifier: Operating System :: POSIX
Classifier: Programming Language :: Python :: 3.9
Classifier: Programming Language :: Python :: 3.10
Classifier: Programming Language :: Python :: 3.11
Classifier: Programming Language :: Python :: 3.12
Classifier: Programming Language :: Python :: 3.13
Classifier: Topic :: Internet
Classifier: Topic :: Scientific/Engineering :: Astronomy
Classifier: Topic :: Scientific/Engineering :: Physics
Requires-Python: >=3.9
License-File: LICENSE.md
Requires-Dist: cryptography>=42
Requires-Dist: igwn-auth-utils>=1.3.0
Requires-Dist: pyjwt
Requires-Dist: requests
Requires-Dist: safe-netrc
Provides-Extra: test
Requires-Dist: pytest; extra == "test"
Requires-Dist: pytest-freezer; extra == "test"
Requires-Dist: pytest-httpserver; extra == "test"
Requires-Dist: pytest-socket; extra == "test"
Dynamic: license-file
